ants_ai-1.0.3.dist-info/METADATA
ants_ai-1.0.3.dist-info/WHEEL
ants_ai-1.0.3.dist-info/licenses/LICENSE
ants_ai.libs/libgcc_s-1e52349c.so.1
ants_ai/assets/hill.png
ants_ai/assets/water.png
ants_ai/assets/RobotoMono-Regular.ttf
ants_ai/py.typed
ants_ai/__init__.py
ants_ai/env.py
ants_ai/ants_ai.pyi
ants_ai/visualizer.py
ants_ai/agents/__init__.py
ants_ai/agents/agent.py
ants_ai/agents/random.py
ants_ai/ants_ai.cpython-312-x86_64-linux-musl.so
ants_ai-1.0.3.dist-info/RECORD
