Metadata-Version: 2.4
Name: ants_ai
Version: 1.0.3
Classifier: Programming Language :: Rust
Classifier: Programming Language :: Python :: Implementation :: CPython
Classifier: Programming Language :: Python :: Implementation :: PyPy
Requires-Dist: gymnasium
Requires-Dist: pygame
Requires-Dist: stable-baselines3[extra]
License-File: LICENSE
Summary: Recreating Google's Ants AI Challenge for AI research.
Author-email: Allan Reyes <allan.rexo@gmail.com>
Maintainer-email: Allan Reyes <allan.rexo@gmail.com>
License: MIT
Requires-Python: >=3.9
Project-URL: Homepage, https://github.com/rey-allan/ants
Project-URL: Repository, https://github.com/rey-allan/ants
Project-URL: Issues, https://github.com/rey-allan/ants/issues
